<?xml version="1.0" encoding="UTF-8"?>
<gresources>
  <gresource prefix="/org/gnome/PasswordSafe">
    <file compressed="true">database.kdbx</file>
    <file compressed="true">passwordsafe.css</file>
    <file compressed="true" preprocess="xml-stripblanks">about_dialog.ui</file>
    <file compressed="true" preprocess="xml-stripblanks">attachment_warning_dialog.ui</file>
    <file preprocess="xml-stripblanks">color_button.ui</file>
    <file preprocess="xml-stripblanks">color_entry_row.ui</file>
    <file compressed="true" preprocess="xml-stripblanks">create_database.ui</file>
    <file compressed="true" preprocess="xml-stripblanks">database_settings_dialog.ui</file>
    <file compressed="true" preprocess="xml-stripblanks">entry_page.ui</file>
    <file preprocess="xml-stripblanks">entry_row.ui</file>
    <file preprocess="xml-stripblanks">group_row.ui</file>
    <file compressed="true" preprocess="xml-stripblanks">group_page.ui</file>
    <file preprocess="xml-stripblanks">icon_widget.ui</file>
    <file preprocess="xml-stripblanks">gtk/create_database_headerbar.ui</file>
    <file compressed="true" preprocess="xml-stripblanks">gtk/edit_element_headerbar.ui</file>
    <file compressed="true" preprocess="xml-stripblanks">gtk/help-overlay.ui</file>
    <file preprocess="xml-stripblanks">gtk/recent_files_headerbar.ui</file>
    <file preprocess="xml-stripblanks">gtk/search_headerbar.ui</file>
    <file preprocess="xml-stripblanks">gtk/selection_mode_headerbar.ui</file>
    <file compressed="true" preprocess="xml-stripblanks">unlock_database.ui</file>
    <file preprocess="xml-stripblanks">unlocked_database.ui</file>
    <file preprocess="xml-stripblanks">unlocked_headerbar.ui</file>
    <file preprocess="xml-stripblanks">main_window.ui</file>
    <file compressed="true" preprocess="xml-stripblanks">notes_dialog.ui</file>
    <file compressed="true" preprocess="xml-stripblanks">notification.ui</file>
    <file preprocess="xml-stripblanks">password_entry_row.ui</file>
    <file compressed="true" preprocess="xml-stripblanks">password_generator_popover.ui</file>
    <file compressed="true" preprocess="xml-stripblanks">properties_dialog.ui</file>
    <file compressed="true" preprocess="xml-stripblanks">references_dialog.ui</file>
    <file compressed="true" preprocess="xml-stripblanks">save_dialog.ui</file>
    <file preprocess="xml-stripblanks">search.ui</file>
    <file compressed="true" preprocess="xml-stripblanks">settings_dialog.ui</file>
    <file compressed="true" preprocess="xml-stripblanks">quit_dialog.ui</file>
    <file compressed="true" preprocess="xml-stripblanks">recent_files_page.ui</file>
    <file compressed="true" preprocess="xml-stripblanks">welcome_page.ui</file>
    <file compressed="true" preprocess="xml-stripblanks">attachment_entry_row.ui</file>
    <file compressed="true" preprocess="xml-stripblanks">attribute_entry_row.ui</file>
    <file compressed="true">crypto/eff_large_wordlist.txt</file>
    <file compressed="true">images/welcome.png</file>
    <file alias="icons/scalable/status/currency-symbolic.svg">icons/currency-symbolic.svg</file>
  </gresource>
</gresources>
